oauth2/__init__.py
oauth2/_compat.py
oauth2/_version.py
oauth2/clients/__init__.py
oauth2/clients/imap.py
oauth2/clients/smtp.py
oauth2_ingaia-1.10.0.post1.dist-info/LICENSE.txt
oauth2_ingaia-1.10.0.post1.dist-info/METADATA
oauth2_ingaia-1.10.0.post1.dist-info/WHEEL
oauth2_ingaia-1.10.0.post1.dist-info/top_level.txt
oauth2_ingaia-1.10.0.post1.dist-info/zip-safe
oauth2_ingaia-1.10.0.post1.dist-info/RECORD
