Metadata-Version: 2.1
Name: oauth2-ingaia
Version: 1.10.0.post1
Summary: library for OAuth version 1.9
Home-page: http://github.com/joestump/python-oauth2
Author: Joe Stump
Author-email: joe@simplegeo.com
License: MIT License
Keywords: oauth
Platform: UNKNOWN
Classifier: Intended Audience :: Developers
Classifier: Programming Language :: Python :: 2
Classifier: Programming Language :: Python :: 2.6
Classifier: Programming Language :: Python :: 2.7
Classifier: Programming Language :: Python :: 3
Classifier: Programming Language :: Python :: 3.3
Classifier: Programming Language :: Python :: 3.4
Classifier: Programming Language :: Python :: Implementation :: CPython
Classifier: Development Status :: 5 - Production/Stable
Classifier: Natural Language :: English
Classifier: License :: OSI Approved :: MIT License
License-File: LICENSE.txt
Requires-Dist: httplib2
